autotime/__init__.py
jupyter_autotime-1.1.0.dist-info/LICENSE
jupyter_autotime-1.1.0.dist-info/WHEEL
jupyter_autotime-1.1.0.dist-info/METADATA
jupyter_autotime-1.1.0.dist-info/RECORD
