Metadata-Version: 2.1
Name: jupyter-autotime
Version: 1.1.0
Summary: Display elapsed time on Jupyter.
Home-page: https://github.com/takelushi/jupyter-autotime
License: MIT
Author: Takeru Saito
Author-email: takelushi@gmail.com
Requires-Python: >=3.6,<4.0
Classifier: License :: OSI Approved :: MIT License
Classifier: Programming Language :: Python :: 3
Classifier: Programming Language :: Python :: 3.6
Classifier: Programming Language :: Python :: 3.7
Classifier: Programming Language :: Python :: 3.8
Requires-Dist: ipython (>=6,<8)
Project-URL: Repository, https://github.com/takelushi/jupyter-autotime
Project-URL: issues, https://github.com/takelushi/jupyter-autotime/issues
